rvq_vae_gpt/__init__.py
rvq_vae_gpt/rvq_vae_gpt.py
rvq_vae_gpt-0.0.4.dist-info/LICENSE
rvq_vae_gpt-0.0.4.dist-info/METADATA
rvq_vae_gpt-0.0.4.dist-info/WHEEL
rvq_vae_gpt-0.0.4.dist-info/top_level.txt
rvq_vae_gpt-0.0.4.dist-info/RECORD
