Metadata-Version: 2.1
Name: rvq-vae-gpt
Version: 0.0.4
Summary: Yet another attempt at GPT in quantized latent space
Home-page: https://github.com/lucidrains/rvq-vae-gpt
Author: Phil Wang
Author-email: lucidrains@gmail.com
License: MIT
Keywords: artificial intelligence,deep learning,transformers,attention mechanism
Classifier: Development Status :: 4 - Beta
Classifier: Intended Audience :: Developers
Classifier: Topic :: Scientific/Engineering :: Artificial Intelligence
Classifier: License :: OSI Approved :: MIT License
Classifier: Programming Language :: Python :: 3.6
License-File: LICENSE
Requires-Dist: beartype
Requires-Dist: einops (>=0.4)
Requires-Dist: local-attention (>=1.0.0)
Requires-Dist: torch (>=1.6)
Requires-Dist: vector-quantize-pytorch (>=1.1.2)
